Metadata-Version: 2.1
Name: mmdeploy
Version: 1.3.1
Summary: OpenMMLab Model Deployment
Home-page: https://github.com/open-mmlab/mmdeploy
Author: OpenMMLab
Author-email: openmmlab@gmail.com
License: Apache License 2.0
Keywords: computer vision,model deployment
Platform: UNKNOWN
Classifier: Development Status :: 3 - Alpha
Classifier: License :: OSI Approved :: Apache Software License
Classifier: Operating System :: OS Independent
Classifier: Programming Language :: Python :: 3
Classifier: Programming Language :: Python :: 3.6
Classifier: Programming Language :: Python :: 3.7
Classifier: Programming Language :: Python :: 3.8
License-File: LICENSE
Requires-Dist: aenum
Requires-Dist: grpcio
Requires-Dist: matplotlib
Requires-Dist: mmengine
Requires-Dist: multiprocess
Requires-Dist: numpy
Requires-Dist: onnx (>=1.13.0)
Requires-Dist: prettytable
Requires-Dist: protobuf (<=3.20.2)
Requires-Dist: six
Requires-Dist: terminaltables
Provides-Extra: all
Requires-Dist: cython ; extra == 'all'
Requires-Dist: numpy ; extra == 'all'
Requires-Dist: packaging ; extra == 'all'
Requires-Dist: setuptools ; extra == 'all'
Requires-Dist: aenum ; extra == 'all'
Requires-Dist: grpcio ; extra == 'all'
Requires-Dist: matplotlib ; extra == 'all'
Requires-Dist: mmengine ; extra == 'all'
Requires-Dist: multiprocess ; extra == 'all'
Requires-Dist: onnx (>=1.13.0) ; extra == 'all'
Requires-Dist: prettytable ; extra == 'all'
Requires-Dist: protobuf (<=3.20.2) ; extra == 'all'
Requires-Dist: six ; extra == 'all'
Requires-Dist: terminaltables ; extra == 'all'
Requires-Dist: asynctest ; extra == 'all'
Requires-Dist: coverage ; extra == 'all'
Requires-Dist: flake8 ; extra == 'all'
Requires-Dist: interrogate ; extra == 'all'
Requires-Dist: isort (==4.3.21) ; extra == 'all'
Requires-Dist: openpyxl (==3.0.9) ; extra == 'all'
Requires-Dist: pandas ; extra == 'all'
Requires-Dist: pytest ; extra == 'all'
Requires-Dist: pyyaml ; extra == 'all'
Requires-Dist: xlrd (==1.2.0) ; extra == 'all'
Requires-Dist: yapf ; extra == 'all'
Requires-Dist: h5py ; extra == 'all'
Requires-Dist: tqdm ; extra == 'all'
Provides-Extra: build
Requires-Dist: cython ; extra == 'build'
Requires-Dist: numpy ; extra == 'build'
Requires-Dist: packaging ; extra == 'build'
Requires-Dist: setuptools ; extra == 'build'
Provides-Extra: optional
Requires-Dist: h5py ; extra == 'optional'
Requires-Dist: tqdm ; extra == 'optional'
Provides-Extra: tests
Requires-Dist: asynctest ; extra == 'tests'
Requires-Dist: coverage ; extra == 'tests'
Requires-Dist: flake8 ; extra == 'tests'
Requires-Dist: interrogate ; extra == 'tests'
Requires-Dist: isort (==4.3.21) ; extra == 'tests'
Requires-Dist: openpyxl (==3.0.9) ; extra == 'tests'
Requires-Dist: pandas ; extra == 'tests'
Requires-Dist: pytest ; extra == 'tests'
Requires-Dist: pyyaml ; extra == 'tests'
Requires-Dist: xlrd (==1.2.0) ; extra == 'tests'
Requires-Dist: yapf ; extra == 'tests'
